docargs/__init__.py
docargs/__main__.py
docargs/check.py
docargs/cli.py
docargs/flake8.py
docargs/identify.py
docargs/version.py
docargs-0.2.0.dist-info/LICENSE
docargs-0.2.0.dist-info/METADATA
docargs-0.2.0.dist-info/WHEEL
docargs-0.2.0.dist-info/entry_points.txt
docargs-0.2.0.dist-info/top_level.txt
docargs-0.2.0.dist-info/RECORD
