Metadata-Version: 2.1
Name: docargs
Version: 0.2.0
Summary: Check that all arguments are documented.
Home-page: https://github.com/janfreyberg/docargs
Author: Jan Freyberg
Author-email: jan@asidatascience.com
License: UNKNOWN
Download-URL: https://github.com/janfreyberg/docargs/0.2.0.tar.gz
Keywords: linting
Platform: UNKNOWN
Requires-Dist: numpydoc
Requires-Dist: click
Requires-Dist: colorama
Requires-Dist: pyyaml
Requires-Dist: flake8
Requires-Dist: docstring-parser
Provides-Extra: test
Requires-Dist: mypy ; extra == 'test'
Requires-Dist: black ; extra == 'test'
Requires-Dist: pytest ; extra == 'test'
Requires-Dist: flake8 ; extra == 'test'
Provides-Extra: tests
Requires-Dist: mypy ; extra == 'tests'
Requires-Dist: black ; extra == 'tests'
Requires-Dist: pytest ; extra == 'tests'
Requires-Dist: flake8 ; extra == 'tests'
